README.rst
setup.py
pywebgettext/__init__.py
pywebgettext/__main__.py
pywebgettext.egg-info/PKG-INFO
pywebgettext.egg-info/SOURCES.txt
pywebgettext.egg-info/dependency_links.txt
pywebgettext.egg-info/entry_points.txt
pywebgettext.egg-info/top_level.txt