Metadata-Version: 1.1
Name: pywebgettext
Version: 0.0.3
Summary: Extract gettext strings from python template
Home-page: http://github.com/maillol/pywebgettext
Author: Vincent MAILLOL
Author-email: pywebgettext@gmail.com
License: WTFPL
Platform: UNKNOWN
Classifier: Programming Language :: Python
Classifier: Development Status :: 4 - Beta
Classifier: Natural Language :: French
Classifier: Operating System :: OS Independent
Classifier: Programming Language :: Python :: 3.4
Classifier: Topic :: Software Development :: Internationalization
